excel_pixel_art/__init__.py
excel_pixel_art/excel_to_image.py
excel_pixel_art/image_to_excel.py
excel_pixel_art-1.0.0.dist-info/METADATA
excel_pixel_art-1.0.0.dist-info/WHEEL
excel_pixel_art-1.0.0.dist-info/entry_points.txt
excel_pixel_art-1.0.0.dist-info/licenses/LICENSE
excel_pixel_art-1.0.0.dist-info/RECORD
