Metadata-Version: 2.4
Name: excel-pixel-art
Version: 1.0.0
Summary: Convert images to Excel pixel art and back
Project-URL: Homepage, https://github.com/luigipascal/excelart
Project-URL: Documentation, https://github.com/luigipascal/excelart#readme
Project-URL: Issues, https://github.com/luigipascal/excelart/issues
Author-email: Rondanini Publishing <info@rondanini.com>
License-Expression: MIT
License-File: LICENSE
Keywords: excel,image-conversion,openpyxl,pixel-art
Classifier: Development Status :: 5 - Production/Stable
Classifier: Intended Audience :: Developers
Classifier: Intended Audience :: End Users/Desktop
Classifier: License :: OSI Approved :: MIT License
Classifier: Programming Language :: Python :: 3
Classifier: Programming Language :: Python :: 3.9
Classifier: Programming Language :: Python :: 3.10
Classifier: Programming Language :: Python :: 3.11
Classifier: Programming Language :: Python :: 3.12
Classifier: Topic :: Multimedia :: Graphics :: Graphics Conversion
Requires-Python: >=3.9
Requires-Dist: numpy>=1.20.0
Requires-Dist: openpyxl>=3.0.0
Requires-Dist: pillow>=9.0.0
Provides-Extra: dev
Requires-Dist: pytest-cov>=4.0.0; extra == 'dev'
Requires-Dist: pytest>=7.0.0; extra == 'dev'
